odoo/addons/stock_barcodes_supplierinfo/README.rst
odoo/addons/stock_barcodes_supplierinfo/__init__.py
odoo/addons/stock_barcodes_supplierinfo/__manifest__.py
odoo/addons/stock_barcodes_supplierinfo/i18n/stock_barcodes_supplierinfo.pot
odoo/addons/stock_barcodes_supplierinfo/readme/CONFIGURE.rst
odoo/addons/stock_barcodes_supplierinfo/readme/CONTRIBUTORS.rst
odoo/addons/stock_barcodes_supplierinfo/readme/DESCRIPTION.rst
odoo/addons/stock_barcodes_supplierinfo/readme/USAGE.rst
odoo/addons/stock_barcodes_supplierinfo/static/description/icon.png
odoo/addons/stock_barcodes_supplierinfo/static/description/index.html
odoo/addons/stock_barcodes_supplierinfo/wizard/__init__.py
odoo/addons/stock_barcodes_supplierinfo/wizard/stock_barcodes_read.py
odoo12_addon_stock_barcodes_supplierinfo-12.0.1.0.2.dist-info/METADATA
odoo12_addon_stock_barcodes_supplierinfo-12.0.1.0.2.dist-info/WHEEL
odoo12_addon_stock_barcodes_supplierinfo-12.0.1.0.2.dist-info/top_level.txt
odoo12_addon_stock_barcodes_supplierinfo-12.0.1.0.2.dist-info/RECORD
