Metadata-Version: 2.1
Name: odoo12-addon-stock-barcodes-supplierinfo
Version: 12.0.1.0.2
Summary: Process products searching them by supplier barcode
Home-page: https://github.com/OCA/stock-logistics-barcode
Author: TAKOBI, Odoo Community Association (OCA)
Author-email: support@odoo-community.org
License: AGPL-3
Platform: UNKNOWN
Classifier: Programming Language :: Python
Classifier: Framework :: Odoo
Classifier: Framework :: Odoo :: 12.0
Classifier: License :: OSI Approved :: GNU Affero General Public License v3
Classifier: Development Status :: 4 - Beta
Requires-Python: >=3.5
Requires-Dist: odoo12-addon-product-supplierinfo-barcode
Requires-Dist: odoo12-addon-stock-barcodes
Requires-Dist: odoo (<12.1dev,>=12.0a)
